{ 
   "softVerticesCombinedSpring" : { 
      "minMminS" : "200", 
      "maxMminS" : "200", 
      "minMmaxS" : "60", 
   }, 
   "softVerticesCombinedDamper" : { 
      "minMminS" : "2.8", 
      "maxMminS" : "2.8", 
      "minMmaxS" : "1.9"
   }, 
   "softVerticesMass" : { 
      "minMminS" : "0.05", 
      "maxMminS" : "0.08", 
      "minMmaxS" : "0.05"
   }, 
   "softVerticesBackForce" : { 
      "minMminS" : "15", 
      "maxMminS" : "18", 
      "minMmaxS" : "4.5"
   }, 
   "softVerticesBackForceThresholdDistance" : { 
      "minMminS" : "0", 
      "maxMminS" : "0", 
      "minMmaxS" : "0"
   }, 
   "softVerticesBackForceMaxForce" : { 
      "minMminS" : "16", 
      "maxMminS" : "22", 
      "minMmaxS" : "7"
   }, 
   "softVerticesColliderRadius" : { 
      "minMminS" : "0.023", 
      "maxMminS" : "0.035", 
      "minMmaxS" : "0.026", 
   }, 
   "softVerticesDistanceLimit" : { 
      "minMminS" : "0.024", 
      "maxMminS" : "0.060", 
      "minMmaxS" : "0.048"
   }, 
   "groupASpringMultiplier" : { 
      "minMminS" : "0.73", 
      "maxMminS" : "0.73", 
      "minMmaxS" : "0.50"
   }, 
   "groupADamperMultiplier" : { 
      "minMminS" : "0.65", 
      "maxMminS" : "0.65", 
      "minMmaxS" : "0.5"
   }, 
   "groupBSpringMultiplier" : { 
      "minMminS" : "1.46", 
      "maxMminS" : "1.46", 
      "minMmaxS" : "1.0"
   }, 
   "groupBDamperMultiplier" : { 
      "minMminS" : "1.3", 
      "maxMminS" : "1.3", 
      "minMmaxS" : "1.0"
   }, 
   "groupCSpringMultiplier" : { 
      "minMminS" : "1.8", 
      "maxMminS" : "1.8", 
      "minMmaxS" : "1.2"
   }, 
   "groupCDamperMultiplier" : { 
      "minMminS" : "1.5", 
      "maxMminS" : "1.5", 
      "minMmaxS" : "1"
   }
}